hydrogpower/__init__.py
hydrogpower/main.py
hydrogpower-0.0.2.dist-info/LICENSE
hydrogpower-0.0.2.dist-info/METADATA
hydrogpower-0.0.2.dist-info/WHEEL
hydrogpower-0.0.2.dist-info/top_level.txt
hydrogpower-0.0.2.dist-info/RECORD
