Metadata-Version: 2.1
Name: hydrogpower
Version: 0.0.2
Summary: A small example package
Author-email: JulianDPastrana <j.pastrana@utp.edu.com>
Project-URL: Homepage, https://github.com/cblancom/natural_gas_project
Classifier: Programming Language :: Python :: 3
Classifier: License :: OSI Approved :: MIT License
Classifier: Operating System :: OS Independent
Requires-Python: >=3.7
License-File: LICENSE
Requires-Dist: numpy
Requires-Dist: pandas
Requires-Dist: openpyxl
Requires-Dist: tensorflow
Requires-Dist: tensorflow-probability
Requires-Dist: gpflow (~=2.8.0)
